scmiac/__init__.py
scmiac/cli.py
scmiac/utils.py
scmiac/evaluation/__init__.py
scmiac/evaluation/benchmark.py
scmiac/evaluation/plot.py
scmiac/modeling/__init__.py
scmiac/modeling/dataset.py
scmiac/modeling/loss.py
scmiac/modeling/model.py
scmiac/modeling/scmiac.py
scmiac/preprocessing/__init__.py
scmiac/preprocessing/anchors.py
scmiac/preprocessing/atacannopy.py
scmiac/preprocessing/cosg.py
scmiac/preprocessing/preprocess.py
scmiac-0.1.0.dist-info/licenses/LICENSE
scmiac-0.1.0.dist-info/METADATA
scmiac-0.1.0.dist-info/WHEEL
scmiac-0.1.0.dist-info/entry_points.txt
scmiac-0.1.0.dist-info/top_level.txt
scmiac-0.1.0.dist-info/RECORD
