Metadata-Version: 2.4
Name: scmiac
Version: 0.1.0
Summary: Single-Cell Multi-modality Integration via cell type filtered Anchors using Contrastive learning
Author: scMIAC Developers
License-Expression: MIT
Project-URL: Homepage, https://github.com/TianLab-Bioinfo/scMIAC
Project-URL: Repository, https://github.com/TianLab-Bioinfo/scMIAC
Project-URL: Documentation, https://github.com/TianLab-Bioinfo/scMIAC/blob/main/docs/tutorial.ipynb
Project-URL: Issues, https://github.com/TianLab-Bioinfo/scMIAC/issues
Keywords: single-cell,multi-modality,integration,contrastive-learning,scRNA-seq,scATAC-seq,bioinformatics
Classifier: Development Status :: 4 - Beta
Classifier: Intended Audience :: Science/Research
Classifier: Programming Language :: Python :: 3
Classifier: Programming Language :: Python :: 3.8
Classifier: Programming Language :: Python :: 3.9
Classifier: Programming Language :: Python :: 3.10
Classifier: Programming Language :: Python :: 3.11
Classifier: Topic :: Scientific/Engineering :: Bio-Informatics
Requires-Python: >=3.8
License-File: LICENSE
Requires-Dist: anndata
Requires-Dist: joblib
Requires-Dist: matplotlib
Requires-Dist: numpy
Requires-Dist: pandas
Requires-Dist: pynndescent
Requires-Dist: scanpy
Requires-Dist: scikit-learn
Requires-Dist: scipy
Requires-Dist: seaborn
Requires-Dist: torch
Requires-Dist: PyYAML
Provides-Extra: test
Requires-Dist: pytest; extra == "test"
Requires-Dist: pytest-mock; extra == "test"
Dynamic: license-file
